{
  "projection_map": {
    "DOC1": "《判决文书1》",
    "DOC2": "《判决文书2》",
    "DOC3": "《判决文书3》",
    "DOC4": "《判决文书4》",
    "DOC5": "《判决文书5》",
    "DOC6": "《判决文书6》",
    "DOC7": "《判决文书7》"
  },
  "structure_description": "Categorization against a closed label set ('赔偿案件', '民事案件', '执行案件'). Records are organized by category, listing document titles that match each category based on evidence keywords like '执行', '民事', or '赔偿'.",
  "records": [
    {
      "category": "赔偿案件",
      "documents": [
        "《判决文书4》",
        "《判决文书7》"
      ]
    },
    {
      "category": "民事案件",
      "documents": [
        "《判决文书6》"
      ]
    },
    {
      "category": "执行案件",
      "documents": [
        "《判决文书1》",
        "《判决文书2》",
        "《判决文书3》",
        "《判决文书5》"
      ]
    }
  ],
  "raw_text": "{\n  \"structure_description\": \"Categorization against a closed label set ('赔偿案件', '民事案件', '执行案件'). Records are organized by category, listing document titles that match each category based on evidence keywords like '执行', '民事', or '赔偿'.\",\n  \"records\": [\n    {\n      \"category\": \"赔偿案件\",\n      \"documents\": [\n        \"《判决文书4》\",\n        \"《判决文书7》\"\n      ]\n    },\n    {\n      \"category\": \"民事案件\",\n      \"documents\": [\n        \"《判决文书6》\"\n      ]\n    },\n    {\n      \"category\": \"执行案件\",\n      \"documents\": [\n        \"《判决文书1》\",\n        \"《判决文书2》\",\n        \"《判决文书3》\",\n        \"《判决文书5》\"\n      ]\n    }\n  ]\n}",
  "doc_sheet_count": 7,
  "evidence_found_count": 7
}