{
  "projection_map": {
    "DOC1": "16,254,884,718.38",
    "DOC2": "华峰超纤",
    "DOC3": "恩捷股份"
  },
  "structure_description": "Entity-targeted enumeration: Documents are categorized into four buckets (High, Medium, Low, Negative) based on their 'Prepayments' values found in evidence.",
  "records": [
    {
      "entity": "16,254,884,718.38",
      "category": "低预付款"
    },
    {
      "entity": "恩捷股份",
      "category": "高预付款"
    }
  ],
  "raw_text": "{\n  \"projection_map\": {\n    \"DOC1\": \"16,254,884,718.38\",\n    \"DOC2\": \"华峰超纤\",\n    \"DOC3\": \"恩捷股份\"\n  },\n  \"structure_description\": \"Entity-targeted enumeration: Documents are categorized into four buckets (High, Medium, Low, Negative) based on their 'Prepayments' values found in evidence.\",\n  \"records\": [\n    {\n      \"entity\": \"16,254,884,718.38\",\n      \"category\": \"低预付款\"\n    },\n    {\n      \"entity\": \"恩捷股份\",\n      \"category\": \"高预付款\"\n    }\n  ]\n}",
  "doc_sheet_count": 3,
  "evidence_found_count": 2
}