{
  "projection_map": {
    "DOC1": "连某1、连某2、连某3、连某4、连某5、连某6继承纠纷案",
    "DOC2": "梁某上诉案",
    "DOC3": "杨某、秦某1、秦某2上诉案",
    "DOC4": "河南省某某建筑防水工程有限公司松原市开发区分公司再审案",
    "DOC5": "霍东琦复议案",
    "DOC6": "谢兴楼、谢丽莉再审案",
    "DOC7": "李某某上诉案",
    "DOC8": "陈义军等与石河子阿玛尼洗护馆相邻关系纠纷案"
  },
  "structure_description": "Enumeration task: map each document to its matching judgment result from the provided list based on verbatim evidence text.",
  "records": [
    {
      "entity": "连某1、连某2、连某3、连某4、连某5、连某6继承纠纷案",
      "matched_result": "判决结果5"
    },
    {
      "entity": "梁某上诉案",
      "matched_result": "判决结果4"
    },
    {
      "entity": "杨某、秦某1、秦某2上诉案",
      "matched_result": "判决结果1"
    },
    {
      "entity": "河南省某某建筑防水工程有限公司松原市开发区分公司再审案",
      "matched_result": "判决结果7"
    },
    {
      "entity": "霍东琦复议案",
      "matched_result": "判决结果2"
    },
    {
      "entity": "谢兴楼、谢丽莉再审案",
      "matched_result": "判决结果8"
    },
    {
      "entity": "李某某上诉案",
      "matched_result": "判决结果6"
    },
    {
      "entity": "陈义军等与石河子阿玛尼洗护馆相邻关系纠纷案",
      "matched_result": "判决结果3"
    }
  ],
  "raw_text": "{\n  \"projection_map\": {\n    \"DOC1\": \"连某1、连某2、连某3、连某4、连某5、连某6继承纠纷案\",\n    \"DOC2\": \"梁某上诉案\",\n    \"DOC3\": \"杨某、秦某1、秦某2上诉案\",\n    \"DOC4\": \"河南省某某建筑防水工程有限公司松原市开发区分公司再审案\",\n    \"DOC5\": \"霍东琦复议案\",\n    \"DOC6\": \"谢兴楼、谢丽莉再审案\",\n    \"DOC7\": \"李某某上诉案\",\n    \"DOC8\": \"陈义军等与石河子阿玛尼洗护馆相邻关系纠纷案\"\n  },\n  \"structure_description\": \"Enumeration task: map each document to its matching judgment result from the provided list based on verbatim evidence text.\",\n  \"records\": [\n    {\"entity\": \"连某1、连某2、连某3、连某4、连某5、连某6继承纠纷案\", \"matched_result\": \"判决结果5\"},\n    {\"entity\": \"梁某上诉案\", \"matched_result\": \"判决结果4\"},\n    {\"entity\": \"杨某、秦某1、秦某2上诉案\", \"matched_result\": \"判决结果1\"},\n    {\"entity\": \"河南省某某建筑防水工程有限公司松原市开发区分公司再审案\", \"matched_result\": \"判决结果7\"},\n    {\"entity\": \"霍东琦复议案\", \"matched_result\": \"判决结果2\"},\n    {\"entity\": \"谢兴楼、谢丽莉再审案\", \"matched_result\": \"判决结果8\"},\n    {\"entity\": \"李某某上诉案\", \"matched_result\": \"判决结果6\"},\n    {\"entity\": \"陈义军等与石河子阿玛尼洗护馆相邻关系纠纷案\", \"matched_result\": \"判决结果3\"}\n  ]\n}",
  "doc_sheet_count": 8,
  "evidence_found_count": 8
}