{
  "projection_map": {
    "DOC1": "汤臣倍健股份有限公司",
    "DOC2": "江苏蔚蓝锂芯股份有限公司",
    "DOC3": "广东拓斯达科技股份有限公司"
  },
  "structure_description": "Cross-entity comparison question asking for '少数股东权益' values in ascending order; records list each company with its value sorted from lowest to highest.",
  "records": [
    {
      "entity": "汤臣倍健股份有限公司",
      "value": "67,802,146.14"
    },
    {
      "entity": "广东拓斯达科技股份有限公司",
      "value": "102,449,276.56"
    },
    {
      "entity": "江苏蔚蓝锂芯股份有限公司",
      "value": "293,936,136.56"
    }
  ],
  "raw_text": "{\n  \"projection_map\": {\n    \"DOC1\": \"汤臣倍健股份有限公司\",\n    \"DOC2\": \"江苏蔚蓝锂芯股份有限公司\",\n    \"DOC3\": \"广东拓斯达科技股份有限公司\"\n  },\n  \"structure_description\": \"Cross-entity comparison question asking for '少数股东权益' values in ascending order; records list each company with its value sorted from lowest to highest.\",\n  \"records\": [\n    {\n      \"entity\": \"汤臣倍健股份有限公司\",\n      \"value\": \"67,802,146.14\"\n    },\n    {\n      \"entity\": \"广东拓斯达科技股份有限公司\",\n      \"value\": \"102,449,276.56\"\n    },\n    {\n      \"entity\": \"江苏蔚蓝锂芯股份有限公司\",\n      \"value\": \"293,936,136.56\"\n    }\n  ]\n}",
  "doc_sheet_count": 3,
  "evidence_found_count": 3
}