{
  "doc_id": "DOC10",
  "doc_title": "《判决文书10》",
  "scan_result": "found",
  "evidence": "[doc_meta DOC10] owner=court_case:判决文书10 | kind=legal_like | case=（2023）鲁01行终1262号\n[DOC10_C001] (score=0.3945)\nmeta: doc=DOC10:《判决文书10》 | owner=court_case:判决文书10 | kind=paragraph | role=legal_argument | time=1947 | case=（2023）鲁01行终1262号 | units=元\n再审申请人（一审原告、二审上诉人）荆某，男，1947年5月16日出生，汉族，住济南市天桥区。\n再审申请人（一审原告、二审上诉人）王某，女，1946年12月4日出生，汉族，住济南市天桥区。\n被申请人（一审被告、二审被上诉人）济南市天桥区人民政府北园街道办事处，住所地济南市天桥区水屯北路2号。\n法定代表人陈岩，主任。\n委托代理人王宝举，山东元序律师事务所律师。\n\n[DOC10_C002] (score=0.3600)\nmeta: doc=DOC10:《判决文书10》 | owner=court_case:判决文书10 | kind=paragraph | time=1974 | case=（2023）鲁01行终1262号\n原审第三人荆小波，男，1974年12月16日出生，汉族，户籍地济南市天桥区。\n原审第三人济南市天桥区北园街道办事处水屯社区居民委员会，住所地济南市天桥区水屯路38号。\n\n[DOC10_C003] (score=0.6061)\nmeta: doc=DOC10:《判决文书10》 | owner=court_case:判决文书10 | kind=paragraph | case=（2023）鲁01行终1262号\n荆某、王某因诉济南市天桥区人民政府北园街道办事处（以下简称北园街道办），原审第三人荆小波及济南市天桥区北园街道办事处水屯社区居民委员会（以下简称水屯居委会）拆迁安置一案，不服济南市中级人民法院（2023）鲁01行终1262号行政裁定，向本院申请再审。本院依法组成合议庭对本案进行了审查，现已审查终结。\n荆某、王某以其申请再审事由符合《中华人民共和国行政诉讼法》第九十一条第三、四项规定为由，向本院申请再审。\n\n[DOC10_C004] (score=0.5217)\nmeta: doc=DOC10:《判决文书10》 | owner=court_case:判决文书10 | kind=paragraph | role=definition | time=2017 | case=（2023）鲁01行终1262号\n本院认为：本案争议焦点是再审申请人提起本案诉讼是否超过法定起诉期限。《最高人民法院关于适用〈中华人民共和国行政诉讼法〉的解释》第九条第一款规定“行政诉讼法第二十条规定的‘因不动产提起的行政诉讼’是指因行政行为导致不动产物权变动而提起的诉讼”。经查，本案争议房屋并未进行不动产登记，尚未发生不动产物权变动。因此，不适用二十年的法定起诉期限。根据原审及本院查明，2017年12月29日，再审申请人荆某与北园街道办、水屯居委会签订涉案安置补偿协议约定：荆某方家庭共有人口11人（包括再审申请人夫妇二人，儿子荆桂林一家三口、儿子荆建强一家三口、儿子荆小波一家三口），选择安置房为60平方米1套、81平方米1套、94平方米1套、141平方米2套。同日，北园街道办、水屯居委会制作“户型选择说明”，其中在“房产姓名”栏，儿媳孟丽洁在60平方米和81平方米房屋处签字，荆小波在94平方米1套处签字，荆桂林、荆小波在141平方米2套处签字。以上在“户型选择说明”上签字的行为，属于再审申请人对安置房屋进行家庭内部分配，北园街道办、水屯居委会对此加盖公章系对安置房屋分配结果的确认。根据《中华人民共和国行政诉讼法》第四十六条规定，其他案件自行政行为作出之日起超过五年提起诉讼的，人民法院不予受理。北园街道办、水屯居委会对安置房屋分配结果的确认行为发生于2017年12月29日，至再审申请人于2023年5月5日提起本案违法之诉已超过五年的法定起诉期限。原审法院认为再审申请人所主张的“登记”行为实际系协议签订行为，其起诉已超过五年的法定起诉期限，并裁定驳回起诉，并无不当。现再审申请人主张由于二人身体不便由三子荆小波代替其办理拆迁安置手续，荆小波未经其授权在94平方米房屋处签字，被申请人将本属于再审申请人的房屋错误登记在荆小波名下，侵害其合法权益，其有权提起诉讼。本院认为，再审申请人虽基于利害关系有权提起诉讼，但是根据《中华人民共和国行政诉讼法》第四十六条规定，提起诉讼应当受起诉期限的限制。再审申请人认可由荆小波代替办理拆迁安置手续，应对其委托荆小波的行为自行承担不利的法律后果。对于荆小波侵害其合法权益事宜，再审申请人可另行向荆小波主张权利。对其再审主张，本院不予支持。\n\n[DOC10_C005] (score=0.5223)\nmeta: doc=DOC10:《判决文书10》 | owner=court_case:判决文书10 | kind=paragraph | case=（2023）鲁01行终1262号\n综上，荆某、王某的再审申请不符合《中华人民共和国行政诉讼法》第九十一条规定的再审情形。依照《最高人民法院关于适用<中华人民共和国行政诉讼法>的解释》第一百一十六条第二款之规定，裁定如下：\n驳回荆某、王某的再审申请。",
  "rounds_used": 1,
  "retrieved_anchors": [
    {
      "anchor_id": "DOC10_C001",
      "retrieval_rank": 3,
      "retrieval_score": 0.3944818377494812,
      "preview": "再审申请人（一审原告、二审上诉人）荆某，男，1947年5月16日出生，汉族，住济南市天桥区。 再审申请人（一审原告、二审上诉人）王某，女，1946年12月4日出生，汉族，住济南市天桥区。 被申请人（一审被告、二审被上诉人）济南市天桥区人民政府北园街道办事处，住所地济南市天桥区水屯北路2号。 法定代表人陈岩，主任。 委托代理人王宝举，山东元序律师事务所律师。",
      "chunk_metadata": {
        "doc_id": "DOC10",
        "doc_title": "《判决文书10》",
        "owner_type": "court_case",
        "owner_name": "判决文书10",
        "doc_kind_hint": "legal_like",
        "section_path": "",
        "content_type": "paragraph",
        "table_header": "",
        "semantic_role": "legal_argument",
        "time_scope": "1947",
        "unit_hints": [
          "元"
        ],
        "case_id": "（2023）鲁01行终1262号"
      }
    },
    {
      "anchor_id": "DOC10_C002",
      "retrieval_rank": 4,
      "retrieval_score": 0.36004090309143066,
      "preview": "原审第三人荆小波，男，1974年12月16日出生，汉族，户籍地济南市天桥区。 原审第三人济南市天桥区北园街道办事处水屯社区居民委员会，住所地济南市天桥区水屯路38号。",
      "chunk_metadata": {
        "doc_id": "DOC10",
        "doc_title": "《判决文书10》",
        "owner_type": "court_case",
        "owner_name": "判决文书10",
        "doc_kind_hint": "legal_like",
        "section_path": "",
        "content_type": "paragraph",
        "table_header": "",
        "semantic_role": "unknown",
        "time_scope": "1974",
        "unit_hints": [],
        "case_id": "（2023）鲁01行终1262号"
      }
    },
    {
      "anchor_id": "DOC10_C003",
      "retrieval_rank": 0,
      "retrieval_score": 0.6060941815376282,
      "preview": "荆某、王某因诉济南市天桥区人民政府北园街道办事处（以下简称北园街道办），原审第三人荆小波及济南市天桥区北园街道办事处水屯社区居民委员会（以下简称水屯居委会）拆迁安置一案，不服济南市中级人民法院（2023）鲁01行终1262号行政裁定，向本院申请再审。本院依法组成合议庭对本案进行了审查，现已审查终结。 荆某、王某以其申请再审事由符合《中华人民共和国行政诉讼法》第九十一条第三、四项规定为由，向本院申请再审。",
      "chunk_metadata": {
        "doc_id": "DOC10",
        "doc_title": "《判决文书10》",
        "owner_type": "court_case",
        "owner_name": "判决文书10",
        "doc_kind_hint": "legal_like",
        "section_path": "",
        "content_type": "paragraph",
        "table_header": "",
        "semantic_role": "unknown",
        "time_scope": "",
        "unit_hints": [],
        "case_id": "（2023）鲁01行终1262号"
      }
    },
    {
      "anchor_id": "DOC10_C004",
      "retrieval_rank": 2,
      "retrieval_score": 0.5216781497001648,
      "preview": "本院认为：本案争议焦点是再审申请人提起本案诉讼是否超过法定起诉期限。《最高人民法院关于适用〈中华人民共和国行政诉讼法〉的解释》第九条第一款规定“行政诉讼法第二十条规定的‘因不动产提起的行政诉讼’是指因行政行为导致不动产物权变动而提起的诉讼”。经查，本案争议房屋并未进行不动产登记，尚未发生不动产物权变动。因此，不适用二十年的法定起诉期限。根据原审及本院查明，2017年12月29日，再审申请人荆某与北园街道办、水屯居委会签订涉案安置补...",
      "chunk_metadata": {
        "doc_id": "DOC10",
        "doc_title": "《判决文书10》",
        "owner_type": "court_case",
        "owner_name": "判决文书10",
        "doc_kind_hint": "legal_like",
        "section_path": "",
        "content_type": "paragraph",
        "table_header": "",
        "semantic_role": "definition",
        "time_scope": "2017",
        "unit_hints": [],
        "case_id": "（2023）鲁01行终1262号"
      }
    },
    {
      "anchor_id": "DOC10_C005",
      "retrieval_rank": 1,
      "retrieval_score": 0.5223401784896851,
      "preview": "综上，荆某、王某的再审申请不符合《中华人民共和国行政诉讼法》第九十一条规定的再审情形。依照《最高人民法院关于适用<中华人民共和国行政诉讼法>的解释》第一百一十六条第二款之规定，裁定如下： 驳回荆某、王某的再审申请。",
      "chunk_metadata": {
        "doc_id": "DOC10",
        "doc_title": "《判决文书10》",
        "owner_type": "court_case",
        "owner_name": "判决文书10",
        "doc_kind_hint": "legal_like",
        "section_path": "",
        "content_type": "paragraph",
        "table_header": "",
        "semantic_role": "unknown",
        "time_scope": "",
        "unit_hints": [],
        "case_id": "（2023）鲁01行终1262号"
      }
    }
  ],
  "doc_metadata": {
    "owner_type": "court_case",
    "owner_name": "判决文书10",
    "doc_kind_hint": "legal_like",
    "doc_case_id": "（2023）鲁01行终1262号",
    "num_tables": 0,
    "num_headings": 0,
    "record_type": "legal"
  }
}