{
  "projection_map": {
    "DOC1": "惠州亿纬锂能股份有限公司",
    "DOC2": "未知",
    "DOC3": "中信博"
  },
  "structure_description": "Entity-targeted lookup for 亿纬锂能's transactional financial liabilities; only DOC1 contains the relevant value.",
  "records": [
    {
      "entity": "惠州亿纬锂能股份有限公司",
      "value": "880,750.00"
    }
  ],
  "raw_text": "{\n  \"projection_map\": {\n    \"DOC1\": \"惠州亿纬锂能股份有限公司\",\n    \"DOC2\": \"未知\",\n    \"DOC3\": \"中信博\"\n  },\n  \"structure_description\": \"Entity-targeted lookup for 亿纬锂能's transactional financial liabilities; only DOC1 contains the relevant value.\",\n  \"records\": [\n    {\n      \"entity\": \"惠州亿纬锂能股份有限公司\",\n      \"value\": \"880,750.00\"\n    }\n  ]\n}",
  "doc_sheet_count": 3,
  "evidence_found_count": 1
}